{
  "ID": [
    "SC1875"
  ],
  "Source": [
    "Human"
  ],
  "Date": [
    "2023-05-23"
  ],
  "Country": [
    "Singapore"
  ],
  "Brand": [
    "nan"
  ],
  "Serotype": [
    "IIIb 61:k:1,5,(7)"
  ],
  "MLST": [
    "ST432"
  ],
  "AST": [
    {
      "Amikacin Interpretation": [
        "I"
      ]
    },
    {
      "Tobramycin Interpretation": [
        "S"
      ]
    },
    {
      "Gentamicin Interpretation": [
        "R"
      ]
    },
    {
      "Amox/K Clav Interpretation": [
        "R"
      ]
    },
    {
      "Amp/Sulbactam Interpretation": [
        "S"
      ]
    },
    {
      "Pip/Tazo Interpretation": [
        "R"
      ]
    },
    {
      "Ampicillin Interpretation": [
        "S"
      ]
    },
    {
      "Piperacillin Interpretation": [
        "I"
      ]
    },
    {
      "Aztreonam Interpretation": [
        "R"
      ]
    },
    {
      "Cefepime Interpretation": [
        "R"
      ]
    },
    {
      "Cefotaxime Interpretation": [
        "R"
      ]
    },
    {
      "Cefoxitin Interpretation": [
        "S"
      ]
    },
    {
      "Ceftazidime Interpretation": [
        "S"
      ]
    },
    {
      "Cefuroxime Interpretation": [
        "R"
      ]
    },
    {
      "Chloramphenicol Interpretation": [
        "I"
      ]
    },
    {
      "Ciprofloxacin Interpretation": [
        "I"
      ]
    },
    {
      "Levofloxacin Interpretation": [
        "I"
      ]
    },
    {
      "Norfloxacin Interpretation": [
        "I"
      ]
    },
    {
      "Colistin Interpretation": [
        "S"
      ]
    },
    {
      "Doripenem Interpretation": [
        "R"
      ]
    },
    {
      "Ertapenem Interpretation": [
        "S"
      ]
    },
    {
      "Imipenem Interpretation": [
        "S"
      ]
    },
    {
      "Meropenem Interpretation": [
        "R"
      ]
    },
    {
      "Fosfomycin Interpretation": [
        "R"
      ]
    },
    {
      "Minocycline Interpretation": [
        "S"
      ]
    },
    {
      "Tetracycline Interpretation": [
        "R"
      ]
    },
    {
      "Nitrofurantoin Interpretation": [
        "R"
      ]
    },
    {
      "Trimeth/Sulfa Interpretation": [
        "I"
      ]
    }
  ],
  "SPI": [
    "HPI",
    "SESS-LEE",
    "SGI2",
    "SPI-3",
    "SPI-4",
    "SPI-5",
    "SPI-6",
    "SPI-7",
    "SPI-8",
    "SPI-9",
    "SPI-13",
    "SPI-14"
  ],
  "AMR": [
    "Aac3-VIa_AGly",
    "Aac6-Aph2_AGly",
    "AacAad_AGly",
    "AadB_AGly",
    "Ant6-Ia_AGly",
    "Aph3--Ia_AGly",
    "Aph3-III_AGly",
    "Aph7_AGly",
    "StrA_AGly",
    "StrB_AGly",
    "VanC1_Gly",
    "VanR-C_Gly",
    "VanS-C_Gly",
    "VanT_Gly",
    "ACI-1_Bla",
    "ACT-MIR_Bla",
    "AmpC1_Ecoli_Bla",
    "AMPH_Ecoli_Bla",
    "CTX-M-2_Bla",
    "CTX-M-8_Bla",
    "DHA_Bla",
    "LAP_Bla",
    "OXA-1_Bla",
    "OXA-2_Bla",
    "OXA-50_Bla",
    "SHV-OKP-LEN_Bla",
    "Arr_Rif",
    "Cat-86_Phe",
    "CatA3_Phe",
    "CatB7_Phe",
    "CmlA_Phe",
    "FexA_Phe",
    "FloR_Phe",
    "DfrA27_Tmt",
    "Erm42_MLS",
    "ErmB_MLS",
    "LinB_MLS",
    "LnuA_MLS",
    "MphA_MLS",
    "FosA2_Fcyn",
    "FosA_Fcyn",
    "Mcr1_Colistin",
    "OqxA_Flq",
    "OqxB_Flq",
    "Qnr-A_Flq",
    "Qnr-S_Flq",
    "QnrB_Flq",
    "TetM_Tet",
    "TetQ_Tet",
    "TetS_Tet",
    "TetW_Tet"
  ],
  "plasmid": [
    "IncHI1A",
    "IncI1-I(Alpha)",
    "IncB/O/K/Z",
    "IncHI2",
    "IncR",
    "IncQ1",
    "IncX1",
    "IncX4",
    "IncFIB(S)",
    "pKPC-CAV1321",
    "ColpVC"
  ]
}