{
  "ID": [
    "SC2526"
  ],
  "Source": [
    "Human"
  ],
  "Date": [
    "2021-04-07"
  ],
  "Country": [
    "Singapore"
  ],
  "Brand": [
    "nan"
  ],
  "Serotype": [
    "Derby"
  ],
  "MLST": [
    "ST71"
  ],
  "AST": [
    {
      "Amikacin Interpretation": [
        "S"
      ]
    },
    {
      "Tobramycin Interpretation": [
        "I"
      ]
    },
    {
      "Gentamicin Interpretation": [
        "R"
      ]
    },
    {
      "Amox/K Clav Interpretation": [
        "I"
      ]
    },
    {
      "Amp/Sulbactam Interpretation": [
        "S"
      ]
    },
    {
      "Pip/Tazo Interpretation": [
        "R"
      ]
    },
    {
      "Ampicillin Interpretation": [
        "S"
      ]
    },
    {
      "Piperacillin Interpretation": [
        "I"
      ]
    },
    {
      "Aztreonam Interpretation": [
        "S"
      ]
    },
    {
      "Cefepime Interpretation": [
        "R"
      ]
    },
    {
      "Cefotaxime Interpretation": [
        "R"
      ]
    },
    {
      "Cefoxitin Interpretation": [
        "S"
      ]
    },
    {
      "Ceftazidime Interpretation": [
        "R"
      ]
    },
    {
      "Cefuroxime Interpretation": [
        "R"
      ]
    },
    {
      "Chloramphenicol Interpretation": [
        "R"
      ]
    },
    {
      "Ciprofloxacin Interpretation": [
        "S"
      ]
    },
    {
      "Levofloxacin Interpretation": [
        "R"
      ]
    },
    {
      "Norfloxacin Interpretation": [
        "S"
      ]
    },
    {
      "Colistin Interpretation": [
        "S"
      ]
    },
    {
      "Doripenem Interpretation": [
        "S"
      ]
    },
    {
      "Ertapenem Interpretation": [
        "R"
      ]
    },
    {
      "Imipenem Interpretation": [
        "I"
      ]
    },
    {
      "Meropenem Interpretation": [
        "R"
      ]
    },
    {
      "Fosfomycin Interpretation": [
        "S"
      ]
    },
    {
      "Minocycline Interpretation": [
        "I"
      ]
    },
    {
      "Tetracycline Interpretation": [
        "I"
      ]
    },
    {
      "Nitrofurantoin Interpretation": [
        "I"
      ]
    },
    {
      "Trimeth/Sulfa Interpretation": [
        "R"
      ]
    }
  ],
  "SPI": [
    "C63PI",
    "CS54_island",
    "HPI",
    "SESS-LEE",
    "SGI1",
    "SPI-6",
    "SPI-7",
    "SPI-8",
    "SPI-9",
    "SPI-14"
  ],
  "AMR": [
    "Aac2-Ia_AGly",
    "Aac3-IIa_AGly",
    "Aac6-Aph2_AGly",
    "Aac6-Iaa_AGly",
    "Aac6-If_AGly",
    "AacAad_AGly",
    "AadA_AGly",
    "AadB_AGly",
    "Ant6-Ia_AGly",
    "Aph3--Ia_AGly",
    "Aph3-IIb_AGly",
    "Aph3-III_AGly",
    "Aph7_AGly",
    "Sat4A_AGly",
    "Sat-2A_AGly",
    "StrA_AGly",
    "StrB_AGly",
    "VanC1_Gly",
    "ACT-MIR_Bla",
    "AmpC1_Ecoli_Bla",
    "AmpC2_Ecoli_Bla",
    "AmpH_Bla",
    "AMPH_Ecoli_Bla",
    "CEPA-85_Bla",
    "CMY_Bla",
    "CTX-M-1_Bla",
    "LAP_Bla",
    "MrdA_Bla",
    "OXA-61_Bla",
    "Arr_Rif",
    "CatB7_Phe",
    "CatBx_Phe",
    "CmlA_Phe",
    "FexA_Phe",
    "DfrA1_Tmt",
    "DfrA5_Tmt",
    "DfrA7_Tmt",
    "DfrA8_Tmt",
    "DfrA23_Tmt",
    "DfrA27_Tmt",
    "SulI_Sul",
    "Erm42_MLS",
    "LinB_MLS",
    "LnuC_MLS",
    "MphA_MLS",
    "FosA_Fcyn",
    "QepA_Flq",
    "QnrB_Flq",
    "TetA_Tet",
    "TetB_Tet",
    "TetC_Tet",
    "TetL_Tet",
    "TetQ_Tet",
    "TetX_Tet"
  ],
  "plasmid": [
    "IncHI1A",
    "IncHI2A",
    "IncI1-I(Alpha)",
    "IncB/O/K/Z",
    "IncN",
    "IncX1",
    "IncX4",
    "IncFII(S)",
    "IncI(Gamma)",
    "pKPC-CAV1321",
    "ColpVC",
    "Col156"
  ]
}