{
  "ID": [
    "SF0124"
  ],
  "Source": [
    "Fruits"
  ],
  "Date": [
    "1900-01-01"
  ],
  "Country": [
    "Malaysia"
  ],
  "Brand": [
    "FM6"
  ],
  "Serotype": [
    "Alachua"
  ],
  "MLST": [
    "ST1298"
  ],
  "AST": [
    {
      "Amikacin Interpretation": [
        "R"
      ]
    },
    {
      "Tobramycin Interpretation": [
        "I"
      ]
    },
    {
      "Gentamicin Interpretation": [
        "S"
      ]
    },
    {
      "Amox/K Clav Interpretation": [
        "I"
      ]
    },
    {
      "Amp/Sulbactam Interpretation": [
        "S"
      ]
    },
    {
      "Pip/Tazo Interpretation": [
        "S"
      ]
    },
    {
      "Ampicillin Interpretation": [
        "S"
      ]
    },
    {
      "Piperacillin Interpretation": [
        "S"
      ]
    },
    {
      "Aztreonam Interpretation": [
        "S"
      ]
    },
    {
      "Cefepime Interpretation": [
        "S"
      ]
    },
    {
      "Cefotaxime Interpretation": [
        "I"
      ]
    },
    {
      "Cefoxitin Interpretation": [
        "R"
      ]
    },
    {
      "Ceftazidime Interpretation": [
        "R"
      ]
    },
    {
      "Cefuroxime Interpretation": [
        "R"
      ]
    },
    {
      "Chloramphenicol Interpretation": [
        "S"
      ]
    },
    {
      "Ciprofloxacin Interpretation": [
        "S"
      ]
    },
    {
      "Levofloxacin Interpretation": [
        "S"
      ]
    },
    {
      "Norfloxacin Interpretation": [
        "S"
      ]
    },
    {
      "Colistin Interpretation": [
        "R"
      ]
    },
    {
      "Doripenem Interpretation": [
        "R"
      ]
    },
    {
      "Ertapenem Interpretation": [
        "I"
      ]
    },
    {
      "Imipenem Interpretation": [
        "R"
      ]
    },
    {
      "Meropenem Interpretation": [
        "I"
      ]
    },
    {
      "Fosfomycin Interpretation": [
        "I"
      ]
    },
    {
      "Minocycline Interpretation": [
        "I"
      ]
    },
    {
      "Tetracycline Interpretation": [
        "S"
      ]
    },
    {
      "Nitrofurantoin Interpretation": [
        "S"
      ]
    },
    {
      "Trimeth/Sulfa Interpretation": [
        "R"
      ]
    }
  ],
  "SPI": [
    "C63PI",
    "HPI",
    "SGI1",
    "SGI2",
    "SPI-1",
    "SPI-2",
    "SPI-3",
    "SPI-10",
    "SPI-12",
    "SPI-14"
  ],
  "AMR": [
    "Aac2-Ia_AGly",
    "Aac3-IIa_AGly",
    "Aac3-Iva_AGly",
    "Aac3-VIa_AGly",
    "Aac6-Aph2_AGly",
    "Aac6-Iaa_AGly",
    "Aac6-If_AGly",
    "Aph3--Ia_AGly",
    "Aph3-IIb_AGly",
    "Aph4-Ia_AGly",
    "Aph7_AGly",
    "AphA2_AGly",
    "Sat4A_AGly",
    "StrB_AGly",
    "VanR-C_Gly",
    "VanS-C_Gly",
    "VanX-Yc_Gly",
    "ACI-1_Bla",
    "AmpC1_Ecoli_Bla",
    "CEPA-85_Bla",
    "CfiA_Bla",
    "CMY_Bla",
    "CTX-M-1_Bla",
    "CTX-M-9_Bla",
    "DHA_Bla",
    "OXA-1_Bla",
    "OXA-61_Bla",
    "SHV-OKP-LEN_Bla",
    "TEM-1D_Bla",
    "Arr_Rif",
    "Cat-86_Phe",
    "CatA1_Phe",
    "CatBx_Phe",
    "CmlA_Phe",
    "FexA_Phe",
    "FloR_Phe",
    "DfrA1_Tmt",
    "DfrA8_Tmt",
    "SulI_Sul",
    "Erm42_MLS",
    "ErmB_MLS",
    "ErmF_MLS",
    "LnuF_MLS",
    "MphA_MLS",
    "FosA2_Fcyn",
    "QepA_Flq",
    "TetB_Tet",
    "TetD_Tet",
    "TetG_Tet",
    "TetL_Tet",
    "TetM_Tet",
    "TetO_Tet",
    "TetQ_Tet",
    "TetS_Tet",
    "TetW_Tet",
    "TetX_Tet"
  ],
  "plasmid": [
    "IncHI1B(R27)",
    "IncHI2",
    "IncR",
    "IncN",
    "IncQ1",
    "IncX1",
    "IncX4",
    "IncFII",
    "IncFII(S)",
    "IncI(Gamma)",
    "ColpVC",
    "Col156",
    "Col440II"
  ]
}