{
  "ID": [
    "SF0701"
  ],
  "Source": [
    "Seafood"
  ],
  "Date": [
    "1900-01-01"
  ],
  "Country": [
    "Malaysia"
  ],
  "Brand": [
    "SM1"
  ],
  "Serotype": [
    "Kentucky"
  ],
  "MLST": [
    "ST198"
  ],
  "AST": [
    {
      "Amikacin Interpretation": [
        "S"
      ]
    },
    {
      "Tobramycin Interpretation": [
        "I"
      ]
    },
    {
      "Gentamicin Interpretation": [
        "S"
      ]
    },
    {
      "Amox/K Clav Interpretation": [
        "I"
      ]
    },
    {
      "Amp/Sulbactam Interpretation": [
        "S"
      ]
    },
    {
      "Pip/Tazo Interpretation": [
        "S"
      ]
    },
    {
      "Ampicillin Interpretation": [
        "I"
      ]
    },
    {
      "Piperacillin Interpretation": [
        "I"
      ]
    },
    {
      "Aztreonam Interpretation": [
        "S"
      ]
    },
    {
      "Cefepime Interpretation": [
        "R"
      ]
    },
    {
      "Cefotaxime Interpretation": [
        "S"
      ]
    },
    {
      "Cefoxitin Interpretation": [
        "R"
      ]
    },
    {
      "Ceftazidime Interpretation": [
        "S"
      ]
    },
    {
      "Cefuroxime Interpretation": [
        "R"
      ]
    },
    {
      "Chloramphenicol Interpretation": [
        "R"
      ]
    },
    {
      "Ciprofloxacin Interpretation": [
        "I"
      ]
    },
    {
      "Levofloxacin Interpretation": [
        "I"
      ]
    },
    {
      "Norfloxacin Interpretation": [
        "I"
      ]
    },
    {
      "Colistin Interpretation": [
        "S"
      ]
    },
    {
      "Doripenem Interpretation": [
        "S"
      ]
    },
    {
      "Ertapenem Interpretation": [
        "R"
      ]
    },
    {
      "Imipenem Interpretation": [
        "I"
      ]
    },
    {
      "Meropenem Interpretation": [
        "R"
      ]
    },
    {
      "Fosfomycin Interpretation": [
        "S"
      ]
    },
    {
      "Minocycline Interpretation": [
        "I"
      ]
    },
    {
      "Tetracycline Interpretation": [
        "I"
      ]
    },
    {
      "Nitrofurantoin Interpretation": [
        "R"
      ]
    },
    {
      "Trimeth/Sulfa Interpretation": [
        "S"
      ]
    }
  ],
  "SPI": [
    "C63PI",
    "CS54_island",
    "HPI",
    "SESS-LEE",
    "SGI1",
    "SPI-1",
    "SPI-2",
    "SPI-4",
    "SPI-5",
    "SPI-7",
    "SPI-11",
    "SPI-13"
  ],
  "AMR": [
    "Aac3-IIa_AGly",
    "AadA_AGly",
    "Aph3-IIb_AGly",
    "StrA_AGly",
    "VanC1_Gly",
    "VanR-C_Gly",
    "VanT_Gly",
    "ACT-MIR_Bla",
    "AmpC2_Ecoli_Bla",
    "AmpH_Bla",
    "CfiA_Bla",
    "CMY_Bla",
    "CTX-M-8_Bla",
    "LAP_Bla",
    "OXA-2_Bla",
    "OXA-50_Bla",
    "Arr_Rif",
    "Cat-86_Phe",
    "CatA1_Phe",
    "CatA3_Phe",
    "DfrA5_Tmt",
    "DfrA7_Tmt",
    "DfrA27_Tmt",
    "SulI_Sul",
    "SulII_Sul",
    "SulIII_Sul",
    "ErmF_MLS",
    "LnuA_MLS",
    "LnuC_MLS",
    "LnuF_MLS",
    "FosA_Fcyn",
    "Mcr3_Colistin",
    "QepA_Flq",
    "Qnr-A_Flq",
    "TetD_Tet",
    "TetL_Tet",
    "TetO_Tet"
  ],
  "plasmid": [
    "IncHI1A",
    "IncHI2A",
    "IncI1-I(Alpha)",
    "IncB/O/K/Z",
    "IncX1",
    "IncFIB(S)",
    "IncI(Gamma)",
    "pKPC-CAV1321",
    "ColpVC"
  ]
}