{
  "ID": [
    "SF1100"
  ],
  "Source": [
    "Pork"
  ],
  "Date": [
    "1900-01-01"
  ],
  "Country": [
    "Brazil"
  ],
  "Brand": [
    "PB8"
  ],
  "Serotype": [
    "Wien"
  ],
  "MLST": [
    "ST102"
  ],
  "AST": [
    {
      "Amikacin Interpretation": [
        "S"
      ]
    },
    {
      "Tobramycin Interpretation": [
        "R"
      ]
    },
    {
      "Gentamicin Interpretation": [
        "S"
      ]
    },
    {
      "Amox/K Clav Interpretation": [
        "S"
      ]
    },
    {
      "Amp/Sulbactam Interpretation": [
        "I"
      ]
    },
    {
      "Pip/Tazo Interpretation": [
        "I"
      ]
    },
    {
      "Ampicillin Interpretation": [
        "R"
      ]
    },
    {
      "Piperacillin Interpretation": [
        "R"
      ]
    },
    {
      "Aztreonam Interpretation": [
        "I"
      ]
    },
    {
      "Cefepime Interpretation": [
        "R"
      ]
    },
    {
      "Cefotaxime Interpretation": [
        "R"
      ]
    },
    {
      "Cefoxitin Interpretation": [
        "R"
      ]
    },
    {
      "Ceftazidime Interpretation": [
        "R"
      ]
    },
    {
      "Cefuroxime Interpretation": [
        "S"
      ]
    },
    {
      "Chloramphenicol Interpretation": [
        "R"
      ]
    },
    {
      "Ciprofloxacin Interpretation": [
        "I"
      ]
    },
    {
      "Levofloxacin Interpretation": [
        "I"
      ]
    },
    {
      "Norfloxacin Interpretation": [
        "R"
      ]
    },
    {
      "Colistin Interpretation": [
        "R"
      ]
    },
    {
      "Doripenem Interpretation": [
        "I"
      ]
    },
    {
      "Ertapenem Interpretation": [
        "R"
      ]
    },
    {
      "Imipenem Interpretation": [
        "S"
      ]
    },
    {
      "Meropenem Interpretation": [
        "I"
      ]
    },
    {
      "Fosfomycin Interpretation": [
        "I"
      ]
    },
    {
      "Minocycline Interpretation": [
        "I"
      ]
    },
    {
      "Tetracycline Interpretation": [
        "S"
      ]
    },
    {
      "Nitrofurantoin Interpretation": [
        "R"
      ]
    },
    {
      "Trimeth/Sulfa Interpretation": [
        "R"
      ]
    }
  ],
  "SPI": [
    "C63PI",
    "SESS-LEE",
    "SPI-1",
    "SPI-3",
    "SPI-6",
    "SPI-9",
    "SPI-10",
    "SPI-11",
    "SPI-12",
    "SPI-13",
    "SPI-14"
  ],
  "AMR": [
    "Aac3-Iva_AGly",
    "Aac6-Aph2_AGly",
    "Aac6-If_AGly",
    "AadB_AGly",
    "Aph3--Ia_AGly",
    "Aph7_AGly",
    "AphA2_AGly",
    "Sat4A_AGly",
    "Sat-2A_AGly",
    "StrA_AGly",
    "VanR-C_Gly",
    "VanT_Gly",
    "ACI-1_Bla",
    "AmpC2_Ecoli_Bla",
    "AmpH_Bla",
    "CEPA-85_Bla",
    "CfiA_Bla",
    "CMY_Bla",
    "CTX-M-2_Bla",
    "CTX-M-8_Bla",
    "LAP_Bla",
    "SHV-OKP-LEN_Bla",
    "Arr_Rif",
    "Cat-86_Phe",
    "CatA1_Phe",
    "CatA3_Phe",
    "CatB7_Phe",
    "DfrA1_Tmt",
    "DfrA5_Tmt",
    "DfrA7_Tmt",
    "DfrA8_Tmt",
    "DfrA23_Tmt",
    "DfrA27_Tmt",
    "LinB_MLS",
    "LnuA_MLS",
    "LnuF_MLS",
    "FosA_Fcyn",
    "Mcr1_Colistin",
    "QepA_Flq",
    "Qnr-A_Flq",
    "TetB_Tet",
    "TetC_Tet",
    "TetL_Tet",
    "TetX_Tet"
  ],
  "plasmid": [
    "IncFIA(HI1)",
    "IncHI2A",
    "IncI1-I(Alpha)",
    "IncHI1B(R27)",
    "IncB/O/K/Z",
    "IncHI2",
    "IncX4",
    "IncFII",
    "IncFII(S)",
    "IncI(Gamma)",
    "pKPC-CAV1321"
  ]
}