{
  "ID": [
    "SF1508"
  ],
  "Source": [
    "Fruits"
  ],
  "Date": [
    "1900-01-01"
  ],
  "Country": [
    "China"
  ],
  "Brand": [
    "FC2"
  ],
  "Serotype": [
    "Oslo"
  ],
  "MLST": [
    "ST1370"
  ],
  "AST": [
    {
      "Amikacin Interpretation": [
        "R"
      ]
    },
    {
      "Tobramycin Interpretation": [
        "S"
      ]
    },
    {
      "Gentamicin Interpretation": [
        "S"
      ]
    },
    {
      "Amox/K Clav Interpretation": [
        "R"
      ]
    },
    {
      "Amp/Sulbactam Interpretation": [
        "R"
      ]
    },
    {
      "Pip/Tazo Interpretation": [
        "S"
      ]
    },
    {
      "Ampicillin Interpretation": [
        "I"
      ]
    },
    {
      "Piperacillin Interpretation": [
        "S"
      ]
    },
    {
      "Aztreonam Interpretation": [
        "I"
      ]
    },
    {
      "Cefepime Interpretation": [
        "R"
      ]
    },
    {
      "Cefotaxime Interpretation": [
        "S"
      ]
    },
    {
      "Cefoxitin Interpretation": [
        "R"
      ]
    },
    {
      "Ceftazidime Interpretation": [
        "R"
      ]
    },
    {
      "Cefuroxime Interpretation": [
        "S"
      ]
    },
    {
      "Chloramphenicol Interpretation": [
        "R"
      ]
    },
    {
      "Ciprofloxacin Interpretation": [
        "S"
      ]
    },
    {
      "Levofloxacin Interpretation": [
        "R"
      ]
    },
    {
      "Norfloxacin Interpretation": [
        "S"
      ]
    },
    {
      "Colistin Interpretation": [
        "R"
      ]
    },
    {
      "Doripenem Interpretation": [
        "R"
      ]
    },
    {
      "Ertapenem Interpretation": [
        "S"
      ]
    },
    {
      "Imipenem Interpretation": [
        "I"
      ]
    },
    {
      "Meropenem Interpretation": [
        "S"
      ]
    },
    {
      "Fosfomycin Interpretation": [
        "I"
      ]
    },
    {
      "Minocycline Interpretation": [
        "R"
      ]
    },
    {
      "Tetracycline Interpretation": [
        "I"
      ]
    },
    {
      "Nitrofurantoin Interpretation": [
        "R"
      ]
    },
    {
      "Trimeth/Sulfa Interpretation": [
        "I"
      ]
    }
  ],
  "SPI": [
    "HPI",
    "SGI1",
    "SPI-2",
    "SPI-4",
    "SPI-6",
    "SPI-9",
    "SPI-11",
    "SPI-14"
  ],
  "AMR": [
    "Aac2-Ia_AGly",
    "Aac3-IIa_AGly",
    "Aac3-VIa_AGly",
    "Aac6-Aph2_AGly",
    "Aac6-If_AGly",
    "Ant6-Ia_AGly",
    "Aph3--Ia_AGly",
    "Aph3-III_AGly",
    "AphA2_AGly",
    "Sat4A_AGly",
    "Sat-2A_AGly",
    "StrB_AGly",
    "VanC1_Gly",
    "VanR-C_Gly",
    "VanS-C_Gly",
    "VanT_Gly",
    "CfiA_Bla",
    "DHA_Bla",
    "OXA-1_Bla",
    "OXA-61_Bla",
    "SHV-OKP-LEN_Bla",
    "TEM-1D_Bla",
    "Cat-86_Phe",
    "CatA2_Phe",
    "CatA3_Phe",
    "CatB7_Phe",
    "CmlA_Phe",
    "FloR_Phe",
    "DfrA1_Tmt",
    "DfrA8_Tmt",
    "SulII_Sul",
    "SulIII_Sul",
    "Erm42_MLS",
    "ErmB_MLS",
    "ErmF_MLS",
    "LnuA_MLS",
    "LnuC_MLS",
    "LnuF_MLS",
    "MphA_MLS",
    "FosA_Fcyn",
    "OqxA_Flq",
    "QepA_Flq",
    "Qnr-A_Flq",
    "TetC_Tet",
    "TetD_Tet",
    "TetG_Tet",
    "TetM_Tet",
    "TetO_Tet",
    "TetQ_Tet",
    "TetS_Tet"
  ],
  "plasmid": [
    "IncHI2A",
    "IncHI1B(R27)",
    "IncB/O/K/Z",
    "IncX4",
    "IncFIB(S)",
    "IncFII",
    "IncFII(S)",
    "IncI(Gamma)",
    "pKPC-CAV1321",
    "ColpVC",
    "Col156",
    "Col440II"
  ]
}