{
  "ID": [
    "SC491"
  ],
  "Source": [
    "Human"
  ],
  "Date": [
    "2022-09-15"
  ],
  "Country": [
    "Singapore"
  ],
  "Brand": [
    "nan"
  ],
  "Serotype": [
    "Potsdam"
  ],
  "MLST": [
    "ST2039"
  ],
  "AST": [
    {
      "Amikacin Interpretation": [
        "R"
      ]
    },
    {
      "Tobramycin Interpretation": [
        "S"
      ]
    },
    {
      "Gentamicin Interpretation": [
        "I"
      ]
    },
    {
      "Amox/K Clav Interpretation": [
        "R"
      ]
    },
    {
      "Amp/Sulbactam Interpretation": [
        "I"
      ]
    },
    {
      "Pip/Tazo Interpretation": [
        "R"
      ]
    },
    {
      "Ampicillin Interpretation": [
        "R"
      ]
    },
    {
      "Piperacillin Interpretation": [
        "R"
      ]
    },
    {
      "Aztreonam Interpretation": [
        "R"
      ]
    },
    {
      "Cefepime Interpretation": [
        "I"
      ]
    },
    {
      "Cefotaxime Interpretation": [
        "R"
      ]
    },
    {
      "Cefoxitin Interpretation": [
        "I"
      ]
    },
    {
      "Ceftazidime Interpretation": [
        "I"
      ]
    },
    {
      "Cefuroxime Interpretation": [
        "I"
      ]
    },
    {
      "Chloramphenicol Interpretation": [
        "R"
      ]
    },
    {
      "Ciprofloxacin Interpretation": [
        "R"
      ]
    },
    {
      "Levofloxacin Interpretation": [
        "R"
      ]
    },
    {
      "Norfloxacin Interpretation": [
        "R"
      ]
    },
    {
      "Colistin Interpretation": [
        "S"
      ]
    },
    {
      "Doripenem Interpretation": [
        "S"
      ]
    },
    {
      "Ertapenem Interpretation": [
        "I"
      ]
    },
    {
      "Imipenem Interpretation": [
        "I"
      ]
    },
    {
      "Meropenem Interpretation": [
        "S"
      ]
    },
    {
      "Fosfomycin Interpretation": [
        "R"
      ]
    },
    {
      "Minocycline Interpretation": [
        "R"
      ]
    },
    {
      "Tetracycline Interpretation": [
        "S"
      ]
    },
    {
      "Nitrofurantoin Interpretation": [
        "R"
      ]
    },
    {
      "Trimeth/Sulfa Interpretation": [
        "I"
      ]
    }
  ],
  "SPI": [
    "CS54_island",
    "HPI",
    "SGI2",
    "SPI-2",
    "SPI-3",
    "SPI-4",
    "SPI-7",
    "SPI-9",
    "SPI-10",
    "SPI-11",
    "SPI-12",
    "SPI-13",
    "SPI-14"
  ],
  "AMR": [
    "Aac6-Aph2_AGly",
    "AadA_AGly",
    "AadB_AGly",
    "Ant6-Ia_AGly",
    "Aph3-IIb_AGly",
    "Aph4-Ia_AGly",
    "Aph7_AGly",
    "StrB_AGly",
    "VanR-C_Gly",
    "ACI-1_Bla",
    "ACT-MIR_Bla",
    "AmpC1_Ecoli_Bla",
    "AmpH_Bla",
    "CEPA-85_Bla",
    "CTX-M-9_Bla",
    "OXA-2_Bla",
    "OXA-61_Bla",
    "SHV-OKP-LEN_Bla",
    "TEM-1D_Bla",
    "CatA1_Phe",
    "CatA3_Phe",
    "CmlA_Phe",
    "FexA_Phe",
    "FloR_Phe",
    "DfrA7_Tmt",
    "DfrA8_Tmt",
    "DfrA23_Tmt",
    "SulI_Sul",
    "SulIII_Sul",
    "Erm42_MLS",
    "ErmB_MLS",
    "ErmF_MLS",
    "LnuC_MLS",
    "LnuF_MLS",
    "MphA_MLS",
    "FosA_Fcyn",
    "Mcr3_Colistin",
    "OqxA_Flq",
    "OqxB_Flq",
    "QepA_Flq",
    "Qnr-S_Flq",
    "TetA_Tet",
    "TetD_Tet",
    "TetG_Tet",
    "TetL_Tet",
    "TetQ_Tet",
    "TetS_Tet",
    "TetW_Tet"
  ],
  "plasmid": [
    "IncFIA(HI1)",
    "IncHI2A",
    "IncHI1B(R27)",
    "IncB/O/K/Z",
    "IncHI2",
    "IncR",
    "IncQ1",
    "IncFIB(S)",
    "IncFII(S)",
    "IncI(Gamma)",
    "pKPC-CAV1321",
    "ColpVC",
    "Col(pHAD28)"
  ]
}