{
  "ID": [
    "SF2085"
  ],
  "Source": [
    "Chicken"
  ],
  "Date": [
    "1900-01-01"
  ],
  "Country": [
    "Brazil"
  ],
  "Brand": [
    "CB7"
  ],
  "Serotype": [
    "Chester"
  ],
  "MLST": [
    "ST343"
  ],
  "AST": [
    {
      "Amikacin Interpretation": [
        "I"
      ]
    },
    {
      "Tobramycin Interpretation": [
        "S"
      ]
    },
    {
      "Gentamicin Interpretation": [
        "R"
      ]
    },
    {
      "Amox/K Clav Interpretation": [
        "S"
      ]
    },
    {
      "Amp/Sulbactam Interpretation": [
        "S"
      ]
    },
    {
      "Pip/Tazo Interpretation": [
        "I"
      ]
    },
    {
      "Ampicillin Interpretation": [
        "R"
      ]
    },
    {
      "Piperacillin Interpretation": [
        "S"
      ]
    },
    {
      "Aztreonam Interpretation": [
        "S"
      ]
    },
    {
      "Cefepime Interpretation": [
        "S"
      ]
    },
    {
      "Cefotaxime Interpretation": [
        "S"
      ]
    },
    {
      "Cefoxitin Interpretation": [
        "S"
      ]
    },
    {
      "Ceftazidime Interpretation": [
        "S"
      ]
    },
    {
      "Cefuroxime Interpretation": [
        "R"
      ]
    },
    {
      "Chloramphenicol Interpretation": [
        "I"
      ]
    },
    {
      "Ciprofloxacin Interpretation": [
        "I"
      ]
    },
    {
      "Levofloxacin Interpretation": [
        "I"
      ]
    },
    {
      "Norfloxacin Interpretation": [
        "S"
      ]
    },
    {
      "Colistin Interpretation": [
        "I"
      ]
    },
    {
      "Doripenem Interpretation": [
        "I"
      ]
    },
    {
      "Ertapenem Interpretation": [
        "I"
      ]
    },
    {
      "Imipenem Interpretation": [
        "I"
      ]
    },
    {
      "Meropenem Interpretation": [
        "S"
      ]
    },
    {
      "Fosfomycin Interpretation": [
        "R"
      ]
    },
    {
      "Minocycline Interpretation": [
        "I"
      ]
    },
    {
      "Tetracycline Interpretation": [
        "S"
      ]
    },
    {
      "Nitrofurantoin Interpretation": [
        "I"
      ]
    },
    {
      "Trimeth/Sulfa Interpretation": [
        "R"
      ]
    }
  ],
  "SPI": [
    "CS54_island",
    "HPI",
    "SESS-LEE",
    "SGI1",
    "SGI2",
    "SPI-4",
    "SPI-9",
    "SPI-13"
  ],
  "AMR": [
    "Aac2-Ia_AGly",
    "Aac3-IIa_AGly",
    "Aac3-VIa_AGly",
    "Aac6-Aph2_AGly",
    "Aac6-Iaa_AGly",
    "Aac6-If_AGly",
    "AacAad_AGly",
    "AadB_AGly",
    "Ant6-Ia_AGly",
    "Aph3--Ia_AGly",
    "Aph4-Ia_AGly",
    "Aph7_AGly",
    "AphA2_AGly",
    "Sat4A_AGly",
    "Sat-2A_AGly",
    "StrA_AGly",
    "StrB_AGly",
    "VanC1_Gly",
    "VanR-C_Gly",
    "ACI-1_Bla",
    "AmpH_Bla",
    "AMPH_Ecoli_Bla",
    "CARB_Bla",
    "CEPA-85_Bla",
    "CTX-M-1_Bla",
    "CTX-M-9_Bla",
    "LAP_Bla",
    "OXA-1_Bla",
    "OXA-2_Bla",
    "SHV-OKP-LEN_Bla",
    "TEM-1D_Bla",
    "Arr_Rif",
    "CatA3_Phe",
    "CatB7_Phe",
    "CatBx_Phe",
    "FexA_Phe",
    "FloR_Phe",
    "DfrA8_Tmt",
    "DfrA23_Tmt",
    "DfrA27_Tmt",
    "SulI_Sul",
    "ErmF_MLS",
    "LnuA_MLS",
    "LnuF_MLS",
    "MphA_MLS",
    "FosA_Fcyn",
    "QepA_Flq",
    "Qnr-S_Flq",
    "TetA_Tet",
    "TetB_Tet",
    "TetD_Tet",
    "TetL_Tet",
    "TetM_Tet",
    "TetO_Tet",
    "TetS_Tet"
  ],
  "plasmid": [
    "IncHI2A",
    "IncI1-I(Alpha)",
    "IncQ1",
    "IncX1",
    "IncX4",
    "IncFIB(S)",
    "IncFII",
    "pKPC-CAV1321",
    "Col440II"
  ]
}