{
  "ID": [
    "SF2256"
  ],
  "Source": [
    "Eggs"
  ],
  "Date": [
    "1900-01-01"
  ],
  "Country": [
    "Malaysia"
  ],
  "Brand": [
    "EM5"
  ],
  "Serotype": [
    "Infantis"
  ],
  "MLST": [
    "ST32"
  ],
  "AST": [
    {
      "Amikacin Interpretation": [
        "I"
      ]
    },
    {
      "Tobramycin Interpretation": [
        "I"
      ]
    },
    {
      "Gentamicin Interpretation": [
        "I"
      ]
    },
    {
      "Amox/K Clav Interpretation": [
        "S"
      ]
    },
    {
      "Amp/Sulbactam Interpretation": [
        "S"
      ]
    },
    {
      "Pip/Tazo Interpretation": [
        "S"
      ]
    },
    {
      "Ampicillin Interpretation": [
        "I"
      ]
    },
    {
      "Piperacillin Interpretation": [
        "S"
      ]
    },
    {
      "Aztreonam Interpretation": [
        "I"
      ]
    },
    {
      "Cefepime Interpretation": [
        "S"
      ]
    },
    {
      "Cefotaxime Interpretation": [
        "I"
      ]
    },
    {
      "Cefoxitin Interpretation": [
        "S"
      ]
    },
    {
      "Ceftazidime Interpretation": [
        "R"
      ]
    },
    {
      "Cefuroxime Interpretation": [
        "R"
      ]
    },
    {
      "Chloramphenicol Interpretation": [
        "I"
      ]
    },
    {
      "Ciprofloxacin Interpretation": [
        "S"
      ]
    },
    {
      "Levofloxacin Interpretation": [
        "I"
      ]
    },
    {
      "Norfloxacin Interpretation": [
        "I"
      ]
    },
    {
      "Colistin Interpretation": [
        "I"
      ]
    },
    {
      "Doripenem Interpretation": [
        "R"
      ]
    },
    {
      "Ertapenem Interpretation": [
        "R"
      ]
    },
    {
      "Imipenem Interpretation": [
        "R"
      ]
    },
    {
      "Meropenem Interpretation": [
        "S"
      ]
    },
    {
      "Fosfomycin Interpretation": [
        "I"
      ]
    },
    {
      "Minocycline Interpretation": [
        "R"
      ]
    },
    {
      "Tetracycline Interpretation": [
        "R"
      ]
    },
    {
      "Nitrofurantoin Interpretation": [
        "S"
      ]
    },
    {
      "Trimeth/Sulfa Interpretation": [
        "R"
      ]
    }
  ],
  "SPI": [
    "CS54_island",
    "HPI",
    "SGI1",
    "SPI-1",
    "SPI-3",
    "SPI-4",
    "SPI-7",
    "SPI-8",
    "SPI-13",
    "SPI-14"
  ],
  "AMR": [
    "Aac2-Ia_AGly",
    "Aac3-IIa_AGly",
    "Aac3-VIa_AGly",
    "Aac6-Aph2_AGly",
    "Aac6-Iaa_AGly",
    "Aac6-If_AGly",
    "AadB_AGly",
    "Ant6-Ia_AGly",
    "Aph3--Ia_AGly",
    "Aph3-IIb_AGly",
    "Aph7_AGly",
    "StrA_AGly",
    "StrB_AGly",
    "VanC1_Gly",
    "VanS-C_Gly",
    "VanT_Gly",
    "ACI-1_Bla",
    "AmpC1_Ecoli_Bla",
    "AmpC2_Ecoli_Bla",
    "AmpH_Bla",
    "AMPH_Ecoli_Bla",
    "CARB_Bla",
    "CfiA_Bla",
    "CMY_Bla",
    "CTX-M-8_Bla",
    "LAP_Bla",
    "MrdA_Bla",
    "OXA-2_Bla",
    "OXA-61_Bla",
    "Arr_Rif",
    "Cat-86_Phe",
    "CatA2_Phe",
    "CatB7_Phe",
    "CatBx_Phe",
    "FloR_Phe",
    "DfrA1_Tmt",
    "DfrA5_Tmt",
    "DfrA23_Tmt",
    "SulII_Sul",
    "LinB_MLS",
    "FosA2_Fcyn",
    "FosA_Fcyn",
    "OqxA_Flq",
    "OqxB_Flq",
    "QepA_Flq",
    "QnrB_Flq",
    "TetA_Tet",
    "TetB_Tet",
    "TetC_Tet",
    "TetG_Tet",
    "TetM_Tet",
    "TetW_Tet",
    "TetX_Tet"
  ],
  "plasmid": [
    "IncI1-I(Alpha)",
    "IncHI1B(R27)",
    "IncB/O/K/Z",
    "IncHI2",
    "IncR",
    "IncQ1",
    "IncFIB(S)",
    "IncFII(S)",
    "IncI(Gamma)",
    "ColpVC",
    "Col156"
  ]
}