{
  "ID": [
    "SF2508"
  ],
  "Source": [
    "Pork"
  ],
  "Date": [
    "1900-01-01"
  ],
  "Country": [
    "Indonesia"
  ],
  "Brand": [
    "PI8"
  ],
  "Serotype": [
    "Amsterdam"
  ],
  "MLST": [
    "ST2090"
  ],
  "AST": [
    {
      "Amikacin Interpretation": [
        "S"
      ]
    },
    {
      "Tobramycin Interpretation": [
        "S"
      ]
    },
    {
      "Gentamicin Interpretation": [
        "S"
      ]
    },
    {
      "Amox/K Clav Interpretation": [
        "S"
      ]
    },
    {
      "Amp/Sulbactam Interpretation": [
        "S"
      ]
    },
    {
      "Pip/Tazo Interpretation": [
        "I"
      ]
    },
    {
      "Ampicillin Interpretation": [
        "R"
      ]
    },
    {
      "Piperacillin Interpretation": [
        "R"
      ]
    },
    {
      "Aztreonam Interpretation": [
        "R"
      ]
    },
    {
      "Cefepime Interpretation": [
        "S"
      ]
    },
    {
      "Cefotaxime Interpretation": [
        "R"
      ]
    },
    {
      "Cefoxitin Interpretation": [
        "R"
      ]
    },
    {
      "Ceftazidime Interpretation": [
        "I"
      ]
    },
    {
      "Cefuroxime Interpretation": [
        "R"
      ]
    },
    {
      "Chloramphenicol Interpretation": [
        "R"
      ]
    },
    {
      "Ciprofloxacin Interpretation": [
        "R"
      ]
    },
    {
      "Levofloxacin Interpretation": [
        "R"
      ]
    },
    {
      "Norfloxacin Interpretation": [
        "R"
      ]
    },
    {
      "Colistin Interpretation": [
        "S"
      ]
    },
    {
      "Doripenem Interpretation": [
        "I"
      ]
    },
    {
      "Ertapenem Interpretation": [
        "R"
      ]
    },
    {
      "Imipenem Interpretation": [
        "R"
      ]
    },
    {
      "Meropenem Interpretation": [
        "R"
      ]
    },
    {
      "Fosfomycin Interpretation": [
        "I"
      ]
    },
    {
      "Minocycline Interpretation": [
        "S"
      ]
    },
    {
      "Tetracycline Interpretation": [
        "R"
      ]
    },
    {
      "Nitrofurantoin Interpretation": [
        "R"
      ]
    },
    {
      "Trimeth/Sulfa Interpretation": [
        "R"
      ]
    }
  ],
  "SPI": [
    "C63PI",
    "SGI1",
    "SPI-2",
    "SPI-8",
    "SPI-10",
    "SPI-11",
    "SPI-12",
    "SPI-13"
  ],
  "AMR": [
    "Aac6-Aph2_AGly",
    "Aac6-If_AGly",
    "AadA_AGly",
    "Ant6-Ia_AGly",
    "Aph3-III_AGly",
    "Aph4-Ia_AGly",
    "AphA2_AGly",
    "VanC1_Gly",
    "VanR-C_Gly",
    "VanT_Gly",
    "AmpC2_Ecoli_Bla",
    "AmpH_Bla",
    "CEPA-85_Bla",
    "CfiA_Bla",
    "CTX-M-1_Bla",
    "CTX-M-8_Bla",
    "MrdA_Bla",
    "OXA-2_Bla",
    "OXA-61_Bla",
    "SHV-OKP-LEN_Bla",
    "TEM-1D_Bla",
    "Arr_Rif",
    "Cat-86_Phe",
    "CatA2_Phe",
    "CatA3_Phe",
    "CatB7_Phe",
    "CatBx_Phe",
    "CmlA_Phe",
    "FloR_Phe",
    "DfrA1_Tmt",
    "DfrA5_Tmt",
    "DfrA7_Tmt",
    "DfrA27_Tmt",
    "DfrA_Tmt",
    "SulII_Sul",
    "Erm42_MLS",
    "ErmF_MLS",
    "LinB_MLS",
    "LnuA_MLS",
    "MphA_MLS",
    "FosA2_Fcyn",
    "FosA_Fcyn",
    "Mcr1_Colistin",
    "Mcr3_Colistin",
    "TetB_Tet",
    "TetM_Tet",
    "TetO_Tet",
    "TetS_Tet",
    "TetW_Tet",
    "TetX_Tet"
  ],
  "plasmid": [
    "IncFIA(HI1)",
    "IncHI1A",
    "IncHI2A",
    "IncI1-I(Alpha)",
    "IncHI1B(R27)",
    "IncHI2",
    "IncR",
    "IncX1",
    "IncX4",
    "IncFII(S)",
    "ColpVC",
    "Col(pHAD28)"
  ]
}