{
  "ID": [
    "SF2619"
  ],
  "Source": [
    "Pork"
  ],
  "Date": [
    "1900-01-01"
  ],
  "Country": [
    "Indonesia"
  ],
  "Brand": [
    "PI11"
  ],
  "Serotype": [
    "Kentucky"
  ],
  "MLST": [
    "ST152"
  ],
  "AST": [
    {
      "Amikacin Interpretation": [
        "S"
      ]
    },
    {
      "Tobramycin Interpretation": [
        "R"
      ]
    },
    {
      "Gentamicin Interpretation": [
        "I"
      ]
    },
    {
      "Amox/K Clav Interpretation": [
        "R"
      ]
    },
    {
      "Amp/Sulbactam Interpretation": [
        "S"
      ]
    },
    {
      "Pip/Tazo Interpretation": [
        "I"
      ]
    },
    {
      "Ampicillin Interpretation": [
        "I"
      ]
    },
    {
      "Piperacillin Interpretation": [
        "I"
      ]
    },
    {
      "Aztreonam Interpretation": [
        "R"
      ]
    },
    {
      "Cefepime Interpretation": [
        "S"
      ]
    },
    {
      "Cefotaxime Interpretation": [
        "S"
      ]
    },
    {
      "Cefoxitin Interpretation": [
        "S"
      ]
    },
    {
      "Ceftazidime Interpretation": [
        "S"
      ]
    },
    {
      "Cefuroxime Interpretation": [
        "R"
      ]
    },
    {
      "Chloramphenicol Interpretation": [
        "I"
      ]
    },
    {
      "Ciprofloxacin Interpretation": [
        "R"
      ]
    },
    {
      "Levofloxacin Interpretation": [
        "R"
      ]
    },
    {
      "Norfloxacin Interpretation": [
        "R"
      ]
    },
    {
      "Colistin Interpretation": [
        "R"
      ]
    },
    {
      "Doripenem Interpretation": [
        "S"
      ]
    },
    {
      "Ertapenem Interpretation": [
        "R"
      ]
    },
    {
      "Imipenem Interpretation": [
        "I"
      ]
    },
    {
      "Meropenem Interpretation": [
        "I"
      ]
    },
    {
      "Fosfomycin Interpretation": [
        "I"
      ]
    },
    {
      "Minocycline Interpretation": [
        "S"
      ]
    },
    {
      "Tetracycline Interpretation": [
        "R"
      ]
    },
    {
      "Nitrofurantoin Interpretation": [
        "R"
      ]
    },
    {
      "Trimeth/Sulfa Interpretation": [
        "S"
      ]
    }
  ],
  "SPI": [
    "C63PI",
    "CS54_island",
    "SESS-LEE",
    "SGI1",
    "SPI-1",
    "SPI-3",
    "SPI-4",
    "SPI-7",
    "SPI-8",
    "SPI-9",
    "SPI-10",
    "SPI-11"
  ],
  "AMR": [
    "Aac3-Iva_AGly",
    "Aac3-VIa_AGly",
    "Aac6-If_AGly",
    "AadA_AGly",
    "AadB_AGly",
    "Aph3--Ia_AGly",
    "Aph3-III_AGly",
    "StrA_AGly",
    "StrB_AGly",
    "VanR-C_Gly",
    "VanX-Yc_Gly",
    "ACI-1_Bla",
    "ACT-MIR_Bla",
    "AmpH_Bla",
    "AMPH_Ecoli_Bla",
    "CEPA-85_Bla",
    "LAP_Bla",
    "MrdA_Bla",
    "OXA-2_Bla",
    "OXA-50_Bla",
    "OXA-61_Bla",
    "TEM-1D_Bla",
    "Cat-86_Phe",
    "CatA1_Phe",
    "CatA2_Phe",
    "CatA3_Phe",
    "CatBx_Phe",
    "CmlA_Phe",
    "DfrA5_Tmt",
    "DfrA7_Tmt",
    "DfrA23_Tmt",
    "SulI_Sul",
    "SulII_Sul",
    "SulIII_Sul",
    "LinB_MLS",
    "MphA_MLS",
    "FosA_Fcyn",
    "Mcr3_Colistin",
    "OqxB_Flq",
    "QepA_Flq",
    "TetC_Tet",
    "TetL_Tet",
    "TetM_Tet",
    "TetO_Tet",
    "TetS_Tet",
    "TetW_Tet"
  ],
  "plasmid": [
    "IncFIA(HI1)",
    "IncHI1A",
    "IncHI2A",
    "IncHI1B(R27)",
    "IncB/O/K/Z",
    "IncHI2",
    "IncX1",
    "IncFII",
    "IncI(Gamma)",
    "pKPC-CAV1321",
    "ColpVC",
    "Col156",
    "Col(pHAD28)"
  ]
}