{
  "ID": [
    "SF3764"
  ],
  "Source": [
    "Pork"
  ],
  "Date": [
    "1900-01-01"
  ],
  "Country": [
    "Australia"
  ],
  "Brand": [
    "PA12"
  ],
  "Serotype": [
    "Heidelberg"
  ],
  "MLST": [
    "ST15"
  ],
  "AST": [
    {
      "Amikacin Interpretation": [
        "S"
      ]
    },
    {
      "Tobramycin Interpretation": [
        "R"
      ]
    },
    {
      "Gentamicin Interpretation": [
        "R"
      ]
    },
    {
      "Amox/K Clav Interpretation": [
        "R"
      ]
    },
    {
      "Amp/Sulbactam Interpretation": [
        "S"
      ]
    },
    {
      "Pip/Tazo Interpretation": [
        "I"
      ]
    },
    {
      "Ampicillin Interpretation": [
        "R"
      ]
    },
    {
      "Piperacillin Interpretation": [
        "S"
      ]
    },
    {
      "Aztreonam Interpretation": [
        "S"
      ]
    },
    {
      "Cefepime Interpretation": [
        "S"
      ]
    },
    {
      "Cefotaxime Interpretation": [
        "R"
      ]
    },
    {
      "Cefoxitin Interpretation": [
        "R"
      ]
    },
    {
      "Ceftazidime Interpretation": [
        "S"
      ]
    },
    {
      "Cefuroxime Interpretation": [
        "I"
      ]
    },
    {
      "Chloramphenicol Interpretation": [
        "I"
      ]
    },
    {
      "Ciprofloxacin Interpretation": [
        "I"
      ]
    },
    {
      "Levofloxacin Interpretation": [
        "S"
      ]
    },
    {
      "Norfloxacin Interpretation": [
        "S"
      ]
    },
    {
      "Colistin Interpretation": [
        "S"
      ]
    },
    {
      "Doripenem Interpretation": [
        "R"
      ]
    },
    {
      "Ertapenem Interpretation": [
        "I"
      ]
    },
    {
      "Imipenem Interpretation": [
        "I"
      ]
    },
    {
      "Meropenem Interpretation": [
        "R"
      ]
    },
    {
      "Fosfomycin Interpretation": [
        "R"
      ]
    },
    {
      "Minocycline Interpretation": [
        "R"
      ]
    },
    {
      "Tetracycline Interpretation": [
        "R"
      ]
    },
    {
      "Nitrofurantoin Interpretation": [
        "I"
      ]
    },
    {
      "Trimeth/Sulfa Interpretation": [
        "S"
      ]
    }
  ],
  "SPI": [
    "C63PI",
    "HPI",
    "SESS-LEE",
    "SPI-2",
    "SPI-3",
    "SPI-4",
    "SPI-5",
    "SPI-6",
    "SPI-7",
    "SPI-10",
    "SPI-11",
    "SPI-14"
  ],
  "AMR": [
    "Aac6-Aph2_AGly",
    "Ant6-Ia_AGly",
    "Aph3-IIb_AGly",
    "Aph4-Ia_AGly",
    "AphA2_AGly",
    "Sat4A_AGly",
    "Sat-2A_AGly",
    "StrB_AGly",
    "VanC1_Gly",
    "VanS-C_Gly",
    "VanT_Gly",
    "VanX-Yc_Gly",
    "ACI-1_Bla",
    "ACT-MIR_Bla",
    "AmpC1_Ecoli_Bla",
    "CfiA_Bla",
    "CMY_Bla",
    "CTX-M-8_Bla",
    "CTX-M-9_Bla",
    "OXA-1_Bla",
    "OXA-61_Bla",
    "Arr_Rif",
    "Cat-86_Phe",
    "CatA2_Phe",
    "CatB7_Phe",
    "FexA_Phe",
    "FloR_Phe",
    "DfrA7_Tmt",
    "DfrA27_Tmt",
    "DfrA_Tmt",
    "SulI_Sul",
    "SulII_Sul",
    "Erm42_MLS",
    "ErmB_MLS",
    "LinB_MLS",
    "LnuA_MLS",
    "FosA2_Fcyn",
    "Mcr1_Colistin",
    "OqxA_Flq",
    "OqxB_Flq",
    "Qnr-A_Flq",
    "TetB_Tet",
    "TetD_Tet",
    "TetL_Tet",
    "TetM_Tet",
    "TetS_Tet",
    "TetX_Tet"
  ],
  "plasmid": [
    "IncB/O/K/Z",
    "IncHI2",
    "IncR",
    "IncN",
    "IncQ1",
    "IncX1",
    "IncFIB(S)",
    "IncFII(S)",
    "Col156",
    "Col(pHAD28)",
    "Col440II"
  ]
}