{
  "ID": [
    "SF3816"
  ],
  "Source": [
    "Seafood"
  ],
  "Date": [
    "1900-01-01"
  ],
  "Country": [
    "Vietnam"
  ],
  "Brand": [
    "SV2"
  ],
  "Serotype": [
    "Typhi"
  ],
  "MLST": [
    "ST2209"
  ],
  "AST": [
    {
      "Amikacin Interpretation": [
        "I"
      ]
    },
    {
      "Tobramycin Interpretation": [
        "R"
      ]
    },
    {
      "Gentamicin Interpretation": [
        "I"
      ]
    },
    {
      "Amox/K Clav Interpretation": [
        "S"
      ]
    },
    {
      "Amp/Sulbactam Interpretation": [
        "I"
      ]
    },
    {
      "Pip/Tazo Interpretation": [
        "R"
      ]
    },
    {
      "Ampicillin Interpretation": [
        "S"
      ]
    },
    {
      "Piperacillin Interpretation": [
        "R"
      ]
    },
    {
      "Aztreonam Interpretation": [
        "S"
      ]
    },
    {
      "Cefepime Interpretation": [
        "R"
      ]
    },
    {
      "Cefotaxime Interpretation": [
        "I"
      ]
    },
    {
      "Cefoxitin Interpretation": [
        "R"
      ]
    },
    {
      "Ceftazidime Interpretation": [
        "S"
      ]
    },
    {
      "Cefuroxime Interpretation": [
        "S"
      ]
    },
    {
      "Chloramphenicol Interpretation": [
        "R"
      ]
    },
    {
      "Ciprofloxacin Interpretation": [
        "S"
      ]
    },
    {
      "Levofloxacin Interpretation": [
        "S"
      ]
    },
    {
      "Norfloxacin Interpretation": [
        "S"
      ]
    },
    {
      "Colistin Interpretation": [
        "R"
      ]
    },
    {
      "Doripenem Interpretation": [
        "I"
      ]
    },
    {
      "Ertapenem Interpretation": [
        "I"
      ]
    },
    {
      "Imipenem Interpretation": [
        "S"
      ]
    },
    {
      "Meropenem Interpretation": [
        "S"
      ]
    },
    {
      "Fosfomycin Interpretation": [
        "R"
      ]
    },
    {
      "Minocycline Interpretation": [
        "R"
      ]
    },
    {
      "Tetracycline Interpretation": [
        "I"
      ]
    },
    {
      "Nitrofurantoin Interpretation": [
        "S"
      ]
    },
    {
      "Trimeth/Sulfa Interpretation": [
        "I"
      ]
    }
  ],
  "SPI": [
    "C63PI",
    "CS54_island",
    "SPI-1",
    "SPI-3",
    "SPI-4",
    "SPI-5",
    "SPI-7",
    "SPI-11",
    "SPI-13"
  ],
  "AMR": [
    "Aac2-Ia_AGly",
    "AacAad_AGly",
    "AadA_AGly",
    "Ant6-Ia_AGly",
    "Aph3-IIb_AGly",
    "AphA2_AGly",
    "Sat4A_AGly",
    "StrB_AGly",
    "VanC1_Gly",
    "VanT_Gly",
    "VanX-Yc_Gly",
    "ACI-1_Bla",
    "ACT-MIR_Bla",
    "AmpC2_Ecoli_Bla",
    "AmpH_Bla",
    "AMPH_Ecoli_Bla",
    "CEPA-85_Bla",
    "CfiA_Bla",
    "CTX-M-1_Bla",
    "CTX-M-2_Bla",
    "DHA_Bla",
    "OXA-50_Bla",
    "TEM-1D_Bla",
    "Arr_Rif",
    "Cat-86_Phe",
    "CatA1_Phe",
    "CatA3_Phe",
    "CatBx_Phe",
    "DfrA1_Tmt",
    "DfrA27_Tmt",
    "SulI_Sul",
    "SulIII_Sul",
    "Erm42_MLS",
    "ErmF_MLS",
    "LinB_MLS",
    "LnuA_MLS",
    "LnuF_MLS",
    "MphA_MLS",
    "FosA2_Fcyn",
    "Mcr3_Colistin",
    "OqxA_Flq",
    "OqxB_Flq",
    "TetD_Tet",
    "TetG_Tet",
    "TetL_Tet",
    "TetO_Tet",
    "TetQ_Tet",
    "TetS_Tet",
    "TetX_Tet"
  ],
  "plasmid": [
    "IncI1-I(Alpha)",
    "IncR",
    "IncN",
    "IncQ1",
    "IncX1",
    "IncFIB(S)",
    "IncFII(S)",
    "IncI(Gamma)",
    "pKPC-CAV1321",
    "ColpVC",
    "Col(pHAD28)"
  ]
}