{
  "ID": [
    "SF3870"
  ],
  "Source": [
    "Pork"
  ],
  "Date": [
    "1900-01-01"
  ],
  "Country": [
    "Indonesia"
  ],
  "Brand": [
    "PI11"
  ],
  "Serotype": [
    "Minnesota"
  ],
  "MLST": [
    "ST3088"
  ],
  "AST": [
    {
      "Amikacin Interpretation": [
        "I"
      ]
    },
    {
      "Tobramycin Interpretation": [
        "S"
      ]
    },
    {
      "Gentamicin Interpretation": [
        "I"
      ]
    },
    {
      "Amox/K Clav Interpretation": [
        "S"
      ]
    },
    {
      "Amp/Sulbactam Interpretation": [
        "R"
      ]
    },
    {
      "Pip/Tazo Interpretation": [
        "I"
      ]
    },
    {
      "Ampicillin Interpretation": [
        "R"
      ]
    },
    {
      "Piperacillin Interpretation": [
        "I"
      ]
    },
    {
      "Aztreonam Interpretation": [
        "I"
      ]
    },
    {
      "Cefepime Interpretation": [
        "R"
      ]
    },
    {
      "Cefotaxime Interpretation": [
        "S"
      ]
    },
    {
      "Cefoxitin Interpretation": [
        "I"
      ]
    },
    {
      "Ceftazidime Interpretation": [
        "I"
      ]
    },
    {
      "Cefuroxime Interpretation": [
        "I"
      ]
    },
    {
      "Chloramphenicol Interpretation": [
        "I"
      ]
    },
    {
      "Ciprofloxacin Interpretation": [
        "S"
      ]
    },
    {
      "Levofloxacin Interpretation": [
        "R"
      ]
    },
    {
      "Norfloxacin Interpretation": [
        "I"
      ]
    },
    {
      "Colistin Interpretation": [
        "S"
      ]
    },
    {
      "Doripenem Interpretation": [
        "I"
      ]
    },
    {
      "Ertapenem Interpretation": [
        "R"
      ]
    },
    {
      "Imipenem Interpretation": [
        "R"
      ]
    },
    {
      "Meropenem Interpretation": [
        "R"
      ]
    },
    {
      "Fosfomycin Interpretation": [
        "S"
      ]
    },
    {
      "Minocycline Interpretation": [
        "S"
      ]
    },
    {
      "Tetracycline Interpretation": [
        "I"
      ]
    },
    {
      "Nitrofurantoin Interpretation": [
        "I"
      ]
    },
    {
      "Trimeth/Sulfa Interpretation": [
        "S"
      ]
    }
  ],
  "SPI": [
    "SGI1",
    "SPI-1",
    "SPI-3",
    "SPI-6",
    "SPI-8",
    "SPI-9",
    "SPI-11",
    "SPI-13"
  ],
  "AMR": [
    "Aac3-Iva_AGly",
    "Aac3-VIa_AGly",
    "Aac6-If_AGly",
    "Ant6-Ia_AGly",
    "Aph3--Ia_AGly",
    "Aph3-IIb_AGly",
    "Aph3-III_AGly",
    "Aph4-Ia_AGly",
    "Aph7_AGly",
    "Sat4A_AGly",
    "Sat-2A_AGly",
    "StrB_AGly",
    "VanR-C_Gly",
    "ACT-MIR_Bla",
    "AmpC2_Ecoli_Bla",
    "AmpH_Bla",
    "AMPH_Ecoli_Bla",
    "CEPA-85_Bla",
    "CfiA_Bla",
    "CTX-M-1_Bla",
    "CTX-M-8_Bla",
    "LAP_Bla",
    "MrdA_Bla",
    "OXA-1_Bla",
    "SHV-OKP-LEN_Bla",
    "TEM-1D_Bla",
    "Cat-86_Phe",
    "CatA1_Phe",
    "CatA2_Phe",
    "CatA3_Phe",
    "CatBx_Phe",
    "CmlA_Phe",
    "FexA_Phe",
    "FloR_Phe",
    "DfrA1_Tmt",
    "DfrA5_Tmt",
    "DfrA8_Tmt",
    "DfrA27_Tmt",
    "SulII_Sul",
    "ErmB_MLS",
    "LinB_MLS",
    "LnuF_MLS",
    "Mcr1_Colistin",
    "OqxA_Flq",
    "QepA_Flq",
    "QnrB_Flq",
    "TetA_Tet",
    "TetB_Tet",
    "TetC_Tet",
    "TetQ_Tet",
    "TetS_Tet",
    "TetX_Tet"
  ],
  "plasmid": [
    "IncHI1A",
    "IncHI2",
    "IncR",
    "IncX1",
    "IncX4",
    "IncFII",
    "IncFII(S)",
    "IncI(Gamma)",
    "pKPC-CAV1321",
    "ColpVC",
    "Col(pHAD28)"
  ]
}